ugreshaper/__init__.py
ugreshaper/ugreshaper.py
ugreshaper-0.0.3.dist-info/LICENSE
ugreshaper-0.0.3.dist-info/METADATA
ugreshaper-0.0.3.dist-info/WHEEL
ugreshaper-0.0.3.dist-info/top_level.txt
ugreshaper-0.0.3.dist-info/RECORD
