Metadata-Version: 2.1
Name: ugreshaper
Version: 0.0.3
Summary: Text reshaper package
Home-page: https://github.com/Abdusalamstd/ugreshaper
Author: Ezmet
Author-email: azmat3111@gmail.com
License: UNKNOWN
Platform: UNKNOWN
Classifier: Programming Language :: Python :: 3
Classifier: License :: OSI Approved :: MIT License
Classifier: Operating System :: OS Independent
Requires-Python: >=3.6
